patito/__init__.py
patito/_docs.py
patito/exceptions.py
patito/polars.py
patito/pydantic.py
patito/validators.py
patito/_pydantic/__init__.py
patito/_pydantic/column_info.py
patito/_pydantic/repr.py
patito/_pydantic/schema.py
patito/_pydantic/dtypes/__init__.py
patito/_pydantic/dtypes/dtypes.py
patito/_pydantic/dtypes/utils.py
patito-0.8.5.dist-info/METADATA
patito-0.8.5.dist-info/WHEEL
patito-0.8.5.dist-info/licenses/LICENSE
patito-0.8.5.dist-info/RECORD
